curlclinet/__init__.py
curlclinet/curlclinet.py
curlclinet-1.0.dist-info/LICENSE
curlclinet-1.0.dist-info/METADATA
curlclinet-1.0.dist-info/WHEEL
curlclinet-1.0.dist-info/top_level.txt
curlclinet-1.0.dist-info/RECORD
