Metadata-Version: 2.1
Name: curlclinet
Version: 1.0
Summary: A simple library for making HTTP requests on Linux, macOS, and Termux systems
Home-page: https://github.com/Psoidh/SimpleClient
Author: Ahmed
Author-email: esszz12345678@gmail.com
Project-URL: Bug Tracker, https://github.com/Psoidh/SimpleClient/issues
Classifier: Programming Language :: Python :: 3
Classifier: License :: OSI Approved :: MIT License
Classifier: Operating System :: POSIX :: Linux
Classifier: Operating System :: MacOS
Classifier: Operating System :: Android
Requires-Python: >=3.6
License-File: LICENSE
